au_address_parser/__init__.py
au_address_parser/addr_parser.py
au_address_parser-1.0.0.dist-info/LICENSE
au_address_parser-1.0.0.dist-info/METADATA
au_address_parser-1.0.0.dist-info/WHEEL
au_address_parser-1.0.0.dist-info/top_level.txt
au_address_parser-1.0.0.dist-info/RECORD
